Workbook

Sheet Orcamento
B1: CASAMENTO DO ANO
B2: Descrição dos Gastos | C2: Forma Pagamento | D2: Categoria | E2: Status | F2: VALOR TOTAL ANO | G2: TOTAL PAGO | H2: Janeiro - 2025 | J2: Fevereiro - 2025 | L2: Março - 2025 | N2: Status Janeiro | O2: Status Fevereiro | P2: Status Março
H3: Previsto | I3: Realizado | J3: Previsto | K3: Realizado | L3: Previsto | M3: Realizado
B4: GASTOS RECORRENTES
B5: Mesada + Ayla | C5: Pix | D5: Família | E5: Pagamento recorrente | F5: 5400 | G5: 5520 | H5: 540 | I5: 540 | J5: 540 | K5: 540 | L5: 540 | M5: 540 | N5: =IF(I5>H5,"ESTOURADO",IF(I5=0,"-","OK")) -> OK | O5: =IF(K5>J5,"ESTOURADO",IF(K5=0,"-","OK")) -> OK | P5: =IF(M5>L5,"ESTOURADO",IF(M5=0,"-","OK")) -> OK
B6: Faculdade Mari | C6: Boleto | D6: Família | E6: Pagamento recorrente | F6: 48960 | G6: 61530 | H6: 5097.5 | I6: 5097.5 | J6: 5097.5 | K6: 5097.5 | L6: 5097.5 | M6: 5097.5 | N6: =IF(I6>H6,"ESTOURADO",IF(I6=0,"-","OK")) -> OK | O6: =IF(K6>J6,"ESTOURADO",IF(K6=0,"-","OK")) -> OK | P6: =IF(M6>L6,"ESTOURADO",IF(M6=0,"-","OK")) -> OK
B7: Terapia | C7: Pix | D7: Pessoal | E7: Pagamento recorrente | F7: 24000 | G7: 15130 | H7: 1200 | I7: 1200 | J7: 3000 | K7: 3000 | L7: 600 | M7: 600 | N7: =IF(I7>H7,"ESTOURADO",IF(I7=0,"-","OK")) -> OK | O7: =IF(K7>J7,"ESTOURADO",IF(K7=0,"-","OK")) -> OK | P7: =IF(M7>L7,"ESTOURADO",IF(M7=0,"-","OK")) -> OK
B8: Faxineira | C8: Pix | D8: Moradia | E8: Pagamento recorrente | F8: 10000 | G8: 21874.98 | H8: 1600 | I8: 1600 | J8: 1600 | K8: 1600 | L8: 1600 | M8: 1600 | N8: =IF(I8>H8,"ESTOURADO",IF(I8=0,"-","OK")) -> OK | O8: =IF(K8>J8,"ESTOURADO",IF(K8=0,"-","OK")) -> OK | P8: =IF(M8>L8,"ESTOURADO",IF(M8=0,"-","OK")) -> OK
B9: Vivo Celular | C9: Cartão de Crédito | D9: Pessoal | E9: Pagamento recorrente | F9: 2700 | G9: 4880.93 | H9: 340 | I9: 340 | J9: 340 | K9: 340 | L9: 340 | M9: 340 | N9: =IF(I9>H9,"ESTOURADO",IF(I9=0,"-","OK")) -> OK | O9: =IF(K9>J9,"ESTOURADO",IF(K9=0,"-","OK")) -> OK | P9: =IF(M9>L9,"ESTOURADO",IF(M9=0,"-","OK")) -> OK
B10: Gympass | C10: Cartão de Crédito | D10: Saúde | E10: Pagamento recorrente | F10: 1500 | G10: 16500 | H10: 1500 | I10: 1500 | J10: 1500 | K10: 1500 | L10: 1500 | M10: 1500 | N10: =IF(I10>H10,"ESTOURADO",IF(I10=0,"-","OK")) -> OK | O10: =IF(K10>J10,"ESTOURADO",IF(K10=0,"-","OK")) -> OK | P10: =IF(M10>L10,"ESTOURADO",IF(M10=0,"-","OK")) -> OK
B11: Cartão XP | C11: Boleto | D11: Pessoal | E11: Pagamento recorrente | F11: 40000 | G11: 10522.95 | H11: 3445.36 | I11: 3445.36 | J11: 3445.36 | K11: 3445.36 | L11: 3445.36 | M11: 3445.36 | N11: =IF(I11>H11,"ESTOURADO",IF(I11=0,"-","OK")) -> OK | O11: =IF(K11>J11,"ESTOURADO",IF(K11=0,"-","OK")) -> OK | P11: =IF(M11>L11,"ESTOURADO",IF(M11=0,"-","OK")) -> OK
B12: Cartão BTG | C12: Boleto | D12: Pessoal | E12: Pagamento recorrente | F12: 100000 | G12: 547244.26 | H12: 26305.84 | I12: 26305.84 | J12: 23993.8 | K12: 23993.8 | L12: 20062.78 | M12: 20062.78 | N12: =IF(I12>H12,"ESTOURADO",IF(I12=0,"-","OK")) -> OK | O12: =IF(K12>J12,"ESTOURADO",IF(K12=0,"-","OK")) -> OK | P12: =IF(M12>L12,"ESTOURADO",IF(M12=0,"-","OK")) -> OK
B13: Cartão AMEX | C13: Débito em conta | D13: Pessoal | E13: Pagamento recorrente | F13: 100000 | G13: 270676.41 | H13: 31217.8 | I13: 31217.8 | J13: 31296.2 | K13: 31296.2 | L13: 81928.33 | M13: 81928.33 | N13: =IF(I13>H13,"ESTOURADO",IF(I13=0,"-","OK")) -> OK | O13: =IF(K13>J13,"ESTOURADO",IF(K13=0,"-","OK")) -> OK | P13: =IF(M13>L13,"ESTOURADO",IF(M13=0,"-","OK")) -> OK
B14: Leo (Aulas natação) | C14: Pix | D14: Saúde | E14: Pagamento recorrente | F14: 100000 | G14: 0 | H14: 0 | I14: 0 | J14: 0 | K14: 0 | L14: 0 | M14: 0 | N14: =IF(I14>H14,"ESTOURADO",IF(I14=0,"-","OK")) -> - | O14: =IF(K14>J14,"ESTOURADO",IF(K14=0,"-","OK")) -> - | P14: =IF(M14>L14,"ESTOURADO",IF(M14=0,"-","OK")) -> -
B15: Contador | C15: Boleto | D15: Empresa Mimacher | E15: Pagamento recorrente | F15: 2180 | G15: 2640 | H15: 218 | I15: 218 | J15: 218 | K15: 218 | L15: 218 | M15: 218 | N15: =IF(I15>H15,"ESTOURADO",IF(I15=0,"-","OK")) -> OK | O15: =IF(K15>J15,"ESTOURADO",IF(K15=0,"-","OK")) -> OK | P15: =IF(M15>L15,"ESTOURADO",IF(M15=0,"-","OK")) -> OK
B16: Guia ISS | C16: Boleto | D16: Empresa Mimacher | E16: Pagamento recorrente | F16: 1553.2 | G16: 1883.96 | H16: 155 | I16: 155 | J16: 155 | K16: 155 | L16: 155 | M16: 155 | N16: =IF(I16>H16,"ESTOURADO",IF(I16=0,"-","OK")) -> OK | O16: =IF(K16>J16,"ESTOURADO",IF(K16=0,"-","OK")) -> OK | P16: =IF(M16>L16,"ESTOURADO",IF(M16=0,"-","OK")) -> OK
... B18: Seguro de Vida | C18: Cartão de Crédito | D18: Empresa Mimacher | E18: Pagamento recorrente | F18: 39020 | G18: 8844 | H18: 737 | I18: 737 | J18: 737 | K18: 737 | L18: 737 | M18: 737 | N18: =IF(I18>H18,"ESTOURADO",IF(I18=0,"-","OK")) -> OK | O18: =IF(K18>J18,"ESTOURADO",IF(K18=0,"-","OK")) -> OK | P18: =IF(M18>L18,"ESTOURADO",IF(M18=0,"-","OK")) -> OK
B20: TOTAL GERAL | H20: =SUM(H5:H18) -> 76258.5 | I20: =SUM(I5:I18) -> 76258.5 | J20: =SUM(J5:J18) -> 75824.86 | K20: =SUM(K5:K18) -> 75824.86 | L20: =SUM(L5:L18) -> 120125.97 | M20: =SUM(M5:M18) -> 120125.97

Sheet MP_Transacoes
A1: ID Pagamento MP | B1: Data | C1: Descrição | D1: Categoria (mapeada) | E1: Valor (R$) | F1: Status MP | G1: Mês Referência
A2: (vazio até rodar mp_sync.py)

Sheet Mapeamento
A1: Legenda: edite a coluna 'Palavra-chave' para casar com a descrição do pagamento no Mercado Pago.
A2: Palavra-chave (contém, sem acento, minúsculo) | B2: Categoria | C2: Descrição dos Gastos (opcional)
A3: mesada | B3: Família | C3: Mesada + Ayla
A4: faculdade | B4: Família | C4: Faculdade Mari
A5: terapia | B5: Pessoal | C5: Terapia
A6: faxineira | B6: Moradia | C6: Faxineira
A7: vivo | B7: Pessoal | C7: Vivo Celular
A8: gympass | B8: Saúde | C8: Gympass
A9: cartao xp | B9: Pessoal | C9: Cartão XP
A10: cartao btg | B10: Pessoal | C10: Cartão BTG
A11: amex | B11: Pessoal | C11: Cartão AMEX
A12: natacao | B12: Saúde | C12: Leo (Aulas natação)
A13: contador | B13: Empresa Mimacher | C13: Contador
... A16: seguro de vida | B16: Empresa Mimacher | C16: Seguro de Vida

Sheet Resumo_MP
A1: RESUMO: Orçamento (Previsto) x Gasto real no Mercado Pago
A2: Categoria | B2: Mês | C2: Previsto (soma) | D2: Gasto Mercado Pago | E2: Saldo | F2: Status
A3: Família | B3: Janeiro - 2025 | C3: =SUMIFS(Orcamento!H5:H18,Orcamento!D5:D18,A3) -> 5637.5 | D3: =SUMIFS(MP_Transacoes!E:E,MP_Transacoes!D:D,A3,MP_Transacoes!G:G,"2025-01") -> 0 | E3: =C3-D3 -> 5637.5 | F3: =IF(D3=0,"sem dados MP",IF(D3>C3,"ESTOURADO","DENTRO DO ORÇAMENTO")) -> sem dados MP
A4: Família | B4: Fevereiro - 2025 | C4: =SUMIFS(Orcamento!J5:J18,Orcamento!D5:D18,A4) -> 5637.5 | D4: =SUMIFS(MP_Transacoes!E:E,MP_Transacoes!D:D,A4,MP_Transacoes!G:G,"2025-02") -> 0 | E4: =C4-D4 -> 5637.5 | F4: =IF(D4=0,"sem dados MP",IF(D4>C4,"ESTOURADO","DENTRO DO ORÇAMENTO")) -> sem dados MP
A5: Família | B5: Março - 2025 | C5: =SUMIFS(Orcamento!L5:L18,Orcamento!D5:D18,A5) -> 5637.5 | D5: =SUMIFS(MP_Transacoes!E:E,MP_Transacoes!D:D,A5,MP_Transacoes!G:G,"2025-03") -> 0 | E5: =C5-D5 -> 5637.5 | F5: =IF(D5=0,"sem dados MP",IF(D5>C5,"ESTOURADO","DENTRO DO ORÇAMENTO")) -> sem dados MP
A6: Pessoal | B6: Janeiro - 2025 | C6: =SUMIFS(Orcamento!H5:H18,Orcamento!D5:D18,A6) -> 62509 | D6: =SUMIFS(MP_Transacoes!E:E,MP_Transacoes!D:D,A6,MP_Transacoes!G:G,"2025-01") -> 0 | E6: =C6-D6 -> 62509 | F6: =IF(D6=0,"sem dados MP",IF(D6>C6,"ESTOURADO","DENTRO DO ORÇAMENTO")) -> sem dados MP
A7: Pessoal | B7: Fevereiro - 2025 | C7: =SUMIFS(Orcamento!J5:J18,Orcamento!D5:D18,A7) -> 62075.36 | D7: =SUMIFS(MP_Transacoes!E:E,MP_Transacoes!D:D,A7,MP_Transacoes!G:G,"2025-02") -> 0 | E7: =C7-D7 -> 62075.36 | F7: =IF(D7=0,"sem dados MP",IF(D7>C7,"ESTOURADO","DENTRO DO ORÇAMENTO")) -> sem dados MP
A8: Pessoal | B8: Março - 2025 | C8: =SUMIFS(Orcamento!L5:L18,Orcamento!D5:D18,A8) -> 106376.47 | D8: =SUMIFS(MP_Transacoes!E:E,MP_Transacoes!D:D,A8,MP_Transacoes!G:G,"2025-03") -> 0 | E8: =C8-D8 -> 106376.47 | F8: =IF(D8=0,"sem dados MP",IF(D8>C8,"ESTOURADO","DENTRO DO ORÇAMENTO")) -> sem dados MP
A9: Moradia | B9: Janeiro - 2025 | C9: =SUMIFS(Orcamento!H5:H18,Orcamento!D5:D18,A9) -> 1600 | D9: =SUMIFS(MP_Transacoes!E:E,MP_Transacoes!D:D,A9,MP_Transacoes!G:G,"2025-01") -> 0 | E9: =C9-D9 -> 1600 | F9: =IF(D9=0,"sem dados MP",IF(D9>C9,"ESTOURADO","DENTRO DO ORÇAMENTO")) -> sem dados MP
A10: Moradia | B10: Fevereiro - 2025 | C10: =SUMIFS(Orcamento!J5:J18,Orcamento!D5:D18,A10) -> 1600 | D10: =SUMIFS(MP_Transacoes!E:E,MP_Transacoes!D:D,A10,MP_Transacoes!G:G,"2025-02") -> 0 | E10: =C10-D10 -> 1600 | F10: =IF(D10=0,"sem dados MP",IF(D10>C10,"ESTOURADO","DENTRO DO ORÇAMENTO")) -> sem dados MP
A11: Moradia | B11: Março - 2025 | C11: =SUMIFS(Orcamento!L5:L18,Orcamento!D5:D18,A11) -> 1600 | D11: =SUMIFS(MP_Transacoes!E:E,MP_Transacoes!D:D,A11,MP_Transacoes!G:G,"2025-03") -> 0 | E11: =C11-D11 -> 1600 | F11: =IF(D11=0,"sem dados MP",IF(D11>C11,"ESTOURADO","DENTRO DO ORÇAMENTO")) -> sem dados MP
A12: Saúde | B12: Janeiro - 2025 | C12: =SUMIFS(Orcamento!H5:H18,Orcamento!D5:D18,A12) -> 1500 | D12: =SUMIFS(MP_Transacoes!E:E,MP_Transacoes!D:D,A12,MP_Transacoes!G:G,"2025-01") -> 0 | E12: =C12-D12 -> 1500 | F12: =IF(D12=0,"sem dados MP",IF(D12>C12,"ESTOURADO","DENTRO DO ORÇAMENTO")) -> sem dados MP
A13: Saúde | B13: Fevereiro - 2025 | C13: =SUMIFS(Orcamento!J5:J18,Orcamento!D5:D18,A13) -> 1500 | D13: =SUMIFS(MP_Transacoes!E:E,MP_Transacoes!D:D,A13,MP_Transacoes!G:G,"2025-02") -> 0 | E13: =C13-D13 -> 1500 | F13: =IF(D13=0,"sem dados MP",IF(D13>C13,"ESTOURADO","DENTRO DO ORÇAMENTO")) -> sem dados MP
A14: Saúde | B14: Março - 2025 | C14: =SUMIFS(Orcamento!L5:L18,Orcamento!D5:D18,A14) -> 1500 | D14: =SUMIFS(MP_Transacoes!E:E,MP_Transacoes!D:D,A14,MP_Transacoes!G:G,"2025-03") -> 0 | E14: =C14-D14 -> 1500 | F14: =IF(D14=0,"sem dados MP",IF(D14>C14,"ESTOURADO","DENTRO DO ORÇAMENTO")) -> sem dados MP
A15: Empresa Mimacher | B15: Janeiro - 2025 | C15: =SUMIFS(Orcamento!H5:H18,Orcamento!D5:D18,A15) -> 5012 | D15: =SUMIFS(MP_Transacoes!E:E,MP_Transacoes!D:D,A15,MP_Transacoes!G:G,"2025-01") -> 0 | E15: =C15-D15 -> 5012 | F15: =IF(D15=0,"sem dados MP",IF(D15>C15,"ESTOURADO","DENTRO DO ORÇAMENTO")) -> sem dados MP
A16: Empresa Mimacher | B16: Fevereiro - 2025 | C16: =SUMIFS(Orcamento!J5:J18,Orcamento!D5:D18,A16) -> 5012 | D16: =SUMIFS(MP_Transacoes!E:E,MP_Transacoes!D:D,A16,MP_Transacoes!G:G,"2025-02") -> 0 | E16: =C16-D16 -> 5012 | F16: =IF(D16=0,"sem dados MP",IF(D16>C16,"ESTOURADO","DENTRO DO ORÇAMENTO")) -> sem dados MP
A17: Empresa Mimacher | B17: Março - 2025 | C17: =SUMIFS(Orcamento!L5:L18,Orcamento!D5:D18,A17) -> 5012 | D17: =SUMIFS(MP_Transacoes!E:E,MP_Transacoes!D:D,A17,MP_Transacoes!G:G,"2025-03") -> 0 | E17: =C17-D17 -> 5012 | F17: =IF(D17=0,"sem dados MP",IF(D17>C17,"ESTOURADO","DENTRO DO ORÇAMENTO")) -> sem dados MP
A19: Nota: 'Gasto Mercado Pago' vem da aba MP_Transacoes, preenchida pelo mp_sync.py. Rode o sync antes de conferir este resumo.
